nimsmo.cpython-38-x86_64-linux-gnu.so
nimsmo/smooth_max.nim
nimsmo/nimsmo.nim
nimsmo/smo.nim
nimsmo/stub.py
nimsmo/shrinking.nim
nimsmo/problem/classification.nim
nimsmo/problem/regression.nim
nimsmo/kernel/lrucache.nim
nimsmo/kernel/base.nim
nimsmo/kernel/cache.nim
nimsmo/kernel/gaussian.nim
nimsmo-0.1.6.dist-info/METADATA
nimsmo-0.1.6.dist-info/WHEEL
nimsmo-0.1.6.dist-info/RECORD
