Metadata-Version: 2.1
Name: nimsmo
Version: 0.1.6
Summary: 
Author: Nico Strasdat
Author-email: Nico.Strasdat@tu-dresden.de
Requires-Python: >=3.8,<4.0
Classifier: Programming Language :: Python :: 3
Classifier: Programming Language :: Python :: 3.8
Classifier: Programming Language :: Python :: 3.9
Classifier: Programming Language :: Python :: 3.10
Classifier: Programming Language :: Python :: 3.11
Requires-Dist: nython (>=0.1.1,<0.2.0)
